{
  "id": "face-fish",
  "countyId": "hualien-county",
  "title": "花蓮鯉魚潭「人面魚」",
  "tag": "都市傳說",
  "scaryLevel": 5,
  "summary": "「魚肉好吃否？」轟動全台的靈異事件。烤熟的吳郭魚身顯現出老太婆的痛苦面容，並開口說話。",
  "location": {
    "display": "花蓮縣壽豐鄉鯉魚潭",
    "district": "壽豐鄉",
    "lat": null,
    "lng": null
  },
  "content": "關於【花蓮鯉魚潭「人面魚」】的傳說在當地流傳已久。事發地點位於花蓮縣壽豐鄉鯉魚潭，這裡常年籠罩著一層神秘的氛圍。據當地老一輩透露，「魚肉好吃否？」轟動全台的靈異事件。烤熟的吳郭魚身顯現出老太婆的痛苦面容，並開口說話。。許多曾親歷此事的目擊者指出，深夜行經此處時，會感到四周溫度驟降，空氣中瀰漫著一股令人窒息的壓抑感。靈異研究者認為，這是因為該地歷史上曾發生過嚴重的意外或衝突，導致強烈的怨氣與執念滯留不散。民俗專家警告，來到此地務必保持敬畏之心，切勿大聲喧嘩或做出不敬之舉，以免招致無法挽回的厄運。至今，每逢農曆七月或是陰雨連綿的深夜，仍不時有驚悚的異象傳出，成為當地人心中揮之不去的禁忌話題。"
}